thaispellcheck/__init__.py
thaispellcheck/sp.model
thaispellcheck-0.2.dist-info/LICENSE
thaispellcheck-0.2.dist-info/METADATA
thaispellcheck-0.2.dist-info/WHEEL
thaispellcheck-0.2.dist-info/top_level.txt
thaispellcheck-0.2.dist-info/RECORD
