Metadata-Version: 2.1
Name: thaispellcheck
Version: 0.2
Summary: Thai Spell Check
Home-page: https://github.com/pythainlp/Thai_Spell_Check
Author: Wannaphong Phatthiyaphaibun
Author-email: wannaphong@yahoo.com
License: Apache Software License 2.0
Keywords: promptpay
Classifier: Development Status :: 3 - Alpha
Classifier: Intended Audience :: Developers
Classifier: License :: OSI Approved :: Apache Software License
Classifier: Programming Language :: Python :: Implementation
License-File: LICENSE
Requires-Dist: pythainlp (>=3.1)
Requires-Dist: sklearn-crfsuite
